[{"pk": 1, "model": "nut.patient", "fields": {"surname_mother": "diarra", "first_name": "alou", "last_name": "dolo", "create_date": "2011-12-01", "DDN_Age": "7ans", "seat": 10}}, {"pk": 2, "model": "nut.patient", "fields": {"surname_mother": "fadiga", "first_name": "ibrahim", "last_name": "fadiga", "create_date": "2011-12-01", "DDN_Age": "7mois", "seat": 10}}, {"pk": 3, "model": "nut.patient", "fields": {"surname_mother": "traor\u00e3\u00a9", "first_name": "assan", "last_name": "coulibaly", "create_date": "2011-12-01", "DDN_Age": "1ans", "seat": 1}}, {"pk": 4, "model": "nut.patient", "fields": {"surname_mother": "coulibaly", "first_name": "r\u00e3\u00a9n\u00e3\u00a9", "last_name": "dakouo", "create_date": "2011-12-01", "DDN_Age": "1.5ans", "seat": 1}}, {"pk": 5, "model": "nut.patient", "fields": {"surname_mother": "kon\u00e3\u00a9", "first_name": "adja", "last_name": "demb\u00e3\u00a9l\u00e3\u00a9", "create_date": "2011-12-01", "DDN_Age": "2.5ans", "seat": 2}}, {"pk": 6, "model": "nut.patient", "fields": {"surname_mother": "faye", "first_name": "arouna", "last_name": "demb\u00e3\u00a9l\u00e3\u00a9", "create_date": "2011-12-01", "DDN_Age": "4.5ans", "seat": 2}}, {"pk": 7, "model": "nut.patient", "fields": {"surname_mother": "lafontaine", "first_name": "celine", "last_name": "dion", "create_date": "2011-12-01", "DDN_Age": "5ans", "seat": 3}}, {"pk": 8, "model": "nut.patient", "fields": {"surname_mother": "diallo", "first_name": "chacka", "last_name": "diarra", "create_date": "2011-12-01", "DDN_Age": "9mois", "seat": 3}}, {"pk": 9, "model": "nut.patient", "fields": {"surname_mother": "djir\u00e3\u00a9", "first_name": "aliou", "last_name": "komota", "create_date": "2011-12-01", "DDN_Age": "10mois", "seat": 4}}, {"pk": 10, "model": "nut.patient", "fields": {"surname_mother": "tour\u00e3\u00a9", "first_name": "samba", "last_name": "koita", "create_date": "2011-12-01", "DDN_Age": "7mois", "seat": 8}}]